llmmanugen/Manuscript.py
llmmanugen/Node.py
llmmanugen/Prompt.py
llmmanugen/Section.py
llmmanugen/__init__.py
llmmanugen/lib.py
tests/__init__.py
tests/test_conversion_methods.py
tests/test_manuscript.py
tests/test_node.py
tests/test_section.py
tests/testrun_for_chatpgpt_ada_pseudoclass_prompt.py
llmmanugen-0.1.12.dist-info/LICENSE
llmmanugen-0.1.12.dist-info/METADATA
llmmanugen-0.1.12.dist-info/WHEEL
llmmanugen-0.1.12.dist-info/top_level.txt
llmmanugen-0.1.12.dist-info/RECORD
