Metadata-Version: 2.1
Name: llmmanugen
Version: 0.1.12
Summary: A Python package for manuscript management, designed to handle hierarchical structures of sections and subsections.
Home-page: https://github.com/markomanninen/llmmanugen
Author: Marko T. Manninen
Author-email: elonmedia@gmail.com
Classifier: Programming Language :: Python :: 3
Classifier: License :: OSI Approved :: MIT License
Classifier: Operating System :: OS Independent
License-File: LICENSE
